LICENSE
MANIFEST.in
README.md
__init__.py
setup.py
dist/pyquickdoc-0.0.8.tar.gz
pyquickdoc/__init__.py
pyquickdoc/pyquickdoc.py
pyquickdoc.egg-info/PKG-INFO
pyquickdoc.egg-info/SOURCES.txt
pyquickdoc.egg-info/dependency_links.txt
pyquickdoc.egg-info/top_level.txt
pyquickdoc/config/__init__.py
pyquickdoc/config/en_dict.py
pyquickdoc/config/zh_dict.py
pyquickdoc/doctype/__init__.py
pyquickdoc/doctype/html_template.py
pyquickdoc/doctype/__pycache__/__init__.cpython-36.pyc
pyquickdoc/doctype/__pycache__/html_template.cpython-36.pyc