Metadata-Version: 1.0
Name: pyquickdoc
Version: 0.0.8
Summary: Python 库的函数接口文档,支持快速生成,并且支持导出 html 与 markdown 文档
Home-page: http://www.52phm.cn
Author: Liang XiaoZhi
Author-email: 2374521450@qq.com
License: Apache
Platform: UNKNOWN
